githubdepchecker/__init__.py
githubdepchecker/githubdepchecker.py
githubdepchecker-1.0.5.dist-info/LICENSE.txt
githubdepchecker-1.0.5.dist-info/METADATA
githubdepchecker-1.0.5.dist-info/WHEEL
githubdepchecker-1.0.5.dist-info/entry_points.txt
githubdepchecker-1.0.5.dist-info/top_level.txt
githubdepchecker-1.0.5.dist-info/RECORD
