Metadata-Version: 2.1
Name: githubdepchecker
Version: 1.0.5
Summary: CLI Tool to check the dependencies of github repositories and create a pull request if packages need to get updated.
Home-page: https://github.com/dyte-submissions/dyte-vit-2022-Shubh0405
Author: Shubh Gupta
Author-email: shubhngupta04@gmail.com
License: Apache License 2.0
Keywords: github,pull-requests,npm,npm-packages,cli-tool
Classifier: Development Status :: 5 - Production/Stable
Classifier: Intended Audience :: Developers
Classifier: Topic :: Software Development :: Build Tools
Classifier: Topic :: System :: Shells
Classifier: Topic :: Utilities
Classifier: License :: OSI Approved :: Apache Software License
Classifier: Programming Language :: Python :: 3.7
Classifier: Programming Language :: Python :: 3.8
Classifier: Programming Language :: Python :: 3.9
Classifier: Programming Language :: Python :: 3.10
Requires-Python: >=3.7
License-File: LICENSE.txt
Requires-Dist: requests
Provides-Extra: dev
Requires-Dist: setuptools ; extra == 'dev'
Requires-Dist: twine ; extra == 'dev'
Requires-Dist: wheel ; extra == 'dev'
